{
  "phasePattern":
  [
    {
      "action_list": [
        {
          "action_name": "buff",
          "args": [ 1 ],
          "jump_action": "next"
        },
        {
          "action_name": "crystal_fixed",
          "args": [ 2 ],
          "jump_action": "next"
        },
        {
          "action_name": "buff",
          "args": [ 2 ],
          "jump_action": "next"
        },
        {
          "action_name": "fireball",
          "args": [ 2 ],
          "jump_action": "next"
        },
        {
          "action_name": "combo",
          "args": [ 2 ],
          "jump_action": "next"
        },
        {
          "action_name": "crystal_chase",
          "args": [ 3 ],
          "jump_action": "next"
        },
        {
          "action_name": "combo",
          "args": [ 2 ],
          "jump_action": "next"
        },
        {
          "action_name": "fireball",
          "args": [ 2 ],
          "jump_action": "next"
        },
        {
          "action_name": "fireball",
          "args": [ 2 ],
          "jump_action": "loop"
        }
      ],
      "jump_condition": "none",
      "loopStartPoint": 1,
      "args": []
    }
  ]
}