{
    "content": {
        "command_list": [
            {
                "command": "SET_BACKGROUND",
                "args": [ "sty_bg_02", -128],
                "end": 1
            },
            {
                "command": "PLAY_BGM",
                "args": [ "BGM_STY_1004"],
                "end": 1
            },
            {
                "command": "BLACKOUT",
                "args": [],
                "end": 1
            },
            {
                "command": "BUTTON_VISIBILITY",
                "args": [ "1" ],
                "end": 1
            },
            {
                "command": "BLACKSCREEN",
                "args": [ "1" ],
                "end": 1
            },
            {
                "command": "BLACKSCREEN_PRINT",
                "args": [ "Regina and Sandalphon work to piece together\n\nreports from the apostles' investigation into demon activity\n\nBut when they are summoned by the pope of the Ilian Church of Grams\n\nThey find themselves placed under arrest on suspicion of treason\n\nFaris's team visits a priest who they believe has evidence that\n\nCardinal Graht is behind the recent string of incidents\n\nThey secure his help, but when his daughter is taken hostage\n\nhe kills himself and the apostles are arrested.\n\nMeanwhile, Nevin's team infiltrates Rozcimea to gather intel on the demonic incidents" ],
                "end": 1
            },
            {
                "command": "BLACKSCREEN_PRINT",
                "args": [],
                "end": 1
            },
            {
                "command": "BLACKSCREEN_PRINT",
                "args": [],
                "end": 1
            },
            {
                "command": "BLACKSCREEN_PRINT",
                "args": [],
                "end": 1
            },
            {
                "command": "BLACKSCREEN_PRINT",
                "args": [],
                "end": 1
            },
            {
                "command": "BLACKSCREEN_PRINT",
                "args": [],
                "end": 1
            },
            {
                "command": "BLACKSCREEN_PRINT",
                "args": [],
                "end": 1
            },
            {
                "command": "BLACKSCREEN_PRINT",
                "args": [],
                "end": 1
            },
            {
                "command": "BLACKSCREEN_PRINT",
                "args": [],
                "end": 1
            },
            {
                "command": "BLACKSCREEN_PRINT",
                "args": [],
                "end": 1
            },
            {
                "command": "BLACKSCREEN_FADE",
                "args": [ "1" ],
                "end": 1
            },
            {
                "command": "DIALOG_FADEIN",
                "args": [],
                "end": 1
            },
            {
                "command": "SET_SPEAKER",
                "args": [ "Guard" ],
                "end": 1
            },
            {
                "command": "PLAY_VOICE",
                "args": [ "VO_STY_100002_001"],
                "end": 1
            },
            {
                "command": "PRINT_DIALOG",
                "args": [ "The vault's secure. Nothing to report." , 1],
                "end": 1
            },
            {
                "command": "DIALOG_FADEOUT",
                "args": [],
                "end": 1
            },
            {
                "command": "DIALOG_FADEIN",
                "args": [],
                "end": 1
            },
            {
                "command": "SET_CHARA",
                "args": [ "8001", "0", "0", "0.0", "-108.0", "1" ],
                "end": 1
            },
            {
                "command": "SET_SPEAKER",
                "args": [ "Guard" ],
                "end": 1
            },
            {
                "command": "PLAY_VOICE",
                "args": [ "VO_STY_100002_002", "1", "0", "1" ],
                "end": 1
            },
            {
                "command": "PRINT_DIALOG",
                "args": [ "Understood. I'll take watch from here.\n\nReturn to your standby location.", "1" ],
                "end": 1
            },
            {
                "command": "DIALOG_FADEOUT",
                "args": [ "1" ],
                "end": 1
            },
            {
                "command": "WAIT",
                "args": [ "0.5" ],
                "end": 1
            },
            {
                "command": "ADD_CHARA",
                "args": [ "102801","900" ],
                "end": 1
            },
            {
                "command": "CHARA_FADE_ANIM",
                "args": [ "102801","IN","0.2", 0 ],
                "end": 1
            },
            {
                "command": "SET_CHARA_SIBLING",
                "args": [ "102801", 0 ],
                "end": 1
            },
            {
                "command": "PORTRAIT_MOVE",
                "args": [ "MOVE","100","-108","2.5" ],
                "end": 1
            },
            {
                "command": "SWITCH_SPEAKER",
                "args": ["8001"],
                "end": 1
            },
            {
                "command": "DIALOG_FADEIN",
                "args": [],
                "end": 1
            },
            {
                "command": "SET_SPEAKER",
                "args": [ "Guard" ],
                "end": 1
            },
            {
                "command": "PLAY_VOICE",
                "args": [ "VO_STY_100002_003", "1", "0", "1" ],
                "end": 1
            },
            {
                "command": "PRINT_DIALOG",
                "args": [ "Hmm?! What's that sound?!", "1" ],
                "end": 1
            },
            {
                "command": "DIALOG_FADEOUT",
                "args": [],
                "end": 1
            },
            {
                "command": "EFFECTS",
                "args": [ "1" ],
                "end": 1
            },
            {
                "command": "SET_CHARA_FACE",
                "args": [ "8001", "1", "0" , 1 ],
                "end": 1
            },
            {
                "command": "PLAY_VOICE",
                "args": [ "VO_STY_100002_004"],
                "end": 1
            },
            {
                "command": "WAIT",
                "args": [ "0.5" ],
                "end": 1
            },
            {
                "command": "PORTRAIT_MOVE",
                "args": [ "MOVE", "0", "-200","0.75"],
                "end": 1
            },
            {
                "command": "PLAY_SE",
                "args": [ "STORY_COMMON_0060", "1" ],
                "end": 1
            },
            {
                "command": "WAIT",
                "args": [ "0.15" ],
                "end": 1
            },
            {
                "command": "CHARA_FADE_ANIM",
                "args": ["102801","OUT","1.5", 0 ],
                "end": 1
            },
            {
                "command": "CHARA_FADE",
                "args": [],
                "end": 1
            },
            {
                "command": "SWITCH_SPEAKER",
                "args": ["102801"],
                "end": 1
            },
            {
                "command": "SET_CHARA",
                "args": [ "102801" ],
                "end": 1
            },
            {
                "command": "PORTRAIT_MOVE",
                "args": [ "JUMP", "down", 15, 1, 1, "InOutSine" ],
                "end": 1
            },
            {
                "command": "DIALOG_FADEIN",
                "args": [],
                "end": 1
            },
            {
                "command": "SET_SPEAKER",
                "args": [ "Nevin" ],
                "end": 1
            },
            {
                "command": "SET_CHARA",
                "args": [ "102801", "0", "0" ],
                "end": 1
            },
            
            {
                "command": "PLAY_VOICE",
                "args": [ "VO_STY_100002_005", "1", "0", "1" ],
                "end": 1
            },
            {
                "command": "PRINT_DIALOG",
                "args": [ "All right, let's get ourselves inside.", "1" ],
                "end": 1
            },
            {
                "command": "DIALOG_FADEOUT",
                "args": [],
                "end": 1
            },
            {
                "command": "TRANSFORM_BLACKSCREEN",
                "args": [ "0", "LEFT", "1.0" ],
                "end": 1
            },
            {
                "command": "PLAY_SE",
                "args": [ "STORY_COMMON_0020", "1" ],
                "end": 1
            },
            {
                "command": "SET_BACKGROUND",
                "args": [ "sty_bg_03" , -128],
                "end": 1
            },
            {
                "command": "WAIT",
                "args": [ 2 ],
                "end": 1
            },
            {
                "command": "DESTROY_PORTRAIT",
                "args": [ "8001" ],
                "end": 1
            },
            {
                "command": "SET_CHARA",
                "args": [ "102801", "0", "0" , 800, -108 ],
                "end": 1
            },
            {
                "command": "TRANSFORM_BLACKSCREEN",
                "args": [ "1", "LEFT", "1.0" ],
                "end": 1
            },
            {
                "command": "PORTRAIT_MOVE",
                "args": [ "WALK", "15", "800.0", "0.0", "1.5" ],
                "end": 1
            },
            {
                "command": "DIALOG_FADEIN",
                "args": [],
                "end": 1
            },
            {
                "command": "SET_SPEAKER",
                "args": [ "Nevin" ],
                "end": 1
            },
            
            {
                "command": "PLAY_VOICE",
                "args": [ "VO_STY_100002_006", "1", "4", "5" ],
                "end": 1
            },
            {
                "command": "PRINT_DIALOG",
                "args": [ "Phew! Finally made it.", "1" ],
                "end": 1
            },
            {
                "command": "DIALOG_FADEOUT",
                "args": [],
                "end": 1
            },
            {
                "command": "SET_CHARA",
                "args": [ "101801", "12", "13", "0", "-108.0", "1" ],
                "end": 1
            },
            {
                "command": "DIALOG_FADEIN",
                "args": [],
                "end": 1
            },
            {
                "command": "SET_SPEAKER",
                "args": [ "Pinon" ],
                "end": 1
            },
            
            {
                "command": "PLAY_VOICE",
                "args": [ "VO_STY_100002_007", "1", "13", "14" , "12","13" ],
                "end": 1
            },
            {
                "command": "PRINT_DIALOG",
                "args": [ "That took a lot longer than I'd hoped.\n\nSecurity's surprisingly tight around here.", "1" ],
                "end": 1
            },
            {
                "command": "DIALOG_FADEOUT",
                "args": [],
                "end": 1
            },
            {
                "command": "SET_CHARA",
                "args": [ "2012", "0", "0" ],
                "end": 1
            },
            {
                "command": "DIALOG_FADEIN",
                "args": [],
                "end": 1
            },
            {
                "command": "SET_SPEAKER",
                "args": [ "Ramiel" ],
                "end": 1
            },
            {
                "command": "PLAY_VOICE",
                "args": [ "VO_STY_100002_008", "1", "0", "1" ],
                "end": 1
            },
            {
                "command": "PRINT_DIALOG",
                "args": [ "We've got less than a half hour before the next shift change,\n\nso we need to find that journal right now.", "1" ],
                "end": 1
            },
            {
                "command": "DIALOG_FADEOUT",
                "args": [],
                "end": 1
            },
            {
                "command": "BLACKIN",
                "args": [],
                "end": 1
            },
            {
                "command": "SET_CHARA",
                "args": [ "102801", "13", "4" ],
                "end": 1
            },
            {
                "command": "BLACKOUT",
                "args": [],
                "end": 1
            },
            {
                "command": "DIALOG_FADEIN",
                "args": [],
                "end": 1
            },
            {
                "command": "SET_CHARA",
                "args": [ "102801", "13", "4", "0", "-108.0", "0" ],
                "end": 1
            },
            {
                "command": "SET_SPEAKER",
                "args": [ "Nevin" ],
                "end": 1
            },
            {
                "command": "PLAY_VOICE",
                "args": [ "VO_STY_100002_009", "1", "4", "5" ,"13", "13"],
                "end": 1
            },
            {
                "command": "PRINT_DIALOG",
                "args": [ "...Damn. No luck.", "1" ],
                "end": 1
            },
            {
                "command": "DIALOG_FADEOUT",
                "args": [],
                "end": 1
            },
            {
                "command": "SET_CHARA",
                "args": [ "2012", "0", "4" ],
                "end": 1
            },
            {
                "command": "DIALOG_FADEIN",
                "args": [],
                "end": 1
            },
            {
                "command": "SET_SPEAKER",
                "args": [ "Ramiel" ],
                "end": 1
            },
            {
                "command": "PLAY_VOICE",
                "args": [ "VO_STY_100002_010", "1", "0", "1", "0", "1" ],
                "end": 1
            },
            {
                "command": "PRINT_DIALOG",
                "args": [ "...Nothing here.", "1" ],
                "end": 1
            },
            {
                "command": "DIALOG_FADEOUT",
                "args": [],
                "end": 1
            },
            {
                "command": "SET_CHARA",
                "args": [ "101801", "12", "13", "0", "-108.0", "0" ],
                "end": 1
            },
            {
                "command": "DIALOG_FADEIN",
                "args": [],
                "end": 1
            },
            {
                "command": "SET_SPEAKER",
                "args": [ "Pinon" ],
                "end": 1
            },
            {
                "command": "PLAY_VOICE",
                "args": [ "VO_STY_100002_011", "1", "13", "14", "12", "13"],
                "end": 1
            },
            {
                "command": "PRINT_DIALOG",
                "args": [ "...Just cobwebs on this end.", "1" ],
                "end": 1
            },
            {
                "command": "DIALOG_FADEOUT",
                "args": [],
                "end": 1
            },
            {
                "command": "SET_CHARA",
                "args": [ "2011", "0", "0" ],
                "end": 1
            },
            {
                "command": "DIALOG_FADEIN",
                "args": [],
                "end": 1
            },
            {
                "command": "SET_SPEAKER",
                "args": [ "Gabriel" ],
                "end": 1
            },
            {
                "command": "PLAY_VOICE",
                "args": [ "VO_STY_100002_012", "1", "0", "2"],
                "end": 1
            },
            {
                "command": "PRINT_DIALOG",
                "args": [ "...Ooo, wait! Is this it?", "1" ],
                "end": 1
            },
            {
                "command": "DIALOG_FADEOUT",
                "args": [],
                "end": 1
            },
            {
                "command": "SET_CHARA",
                "args": [ "2011","0","1","0","-108.0","1" ],
                "end": 1
            },
            {
                "command": "PLAY_SE",
                "args": [ "STORY_COMMON_0022", "1" ],
                "end": 1
            },
            {
                "command": "WAIT",
                "args": [0.6],
                "end": 1
            },
            {
                "command": "DIALOG_FADEIN",
                "args": [],
                "end": 1
            },
            {
                "command": "SET_SPEAKER",
                "args": [ "Gabriel" ],
                "end": 1
            },
            {
                "command": "PLAY_VOICE",
                "args": [ "VO_STY_100002_013", "1", "0", "2"],
                "end": 1
            },
            {
                "command": "PRINT_DIALOG",
                "args": [ "Sealing stone... Five Archdemons...\n\nSatan's resurrection...", "1" ],
                "end": 1
            },
            {
                "command": "DIALOG_FADEOUT",
                "args": [],
                "end": 1
            },
            {
                "command": "SET_CHARA",
                "args": [ "101801", "8", "9", "0", "-108.0", "0" ],
                "end": 1
            },
            {
                "command": "DIALOG_FADEIN",
                "args": [],
                "end": 1
            },
            {
                "command": "SET_SPEAKER",
                "args": [ "Pinon" ],
                "end": 1
            },
            {
                "command": "PLAY_VOICE",
                "args": [ "VO_STY_100002_014", "1", "9", "10", "8", "9"],
                "end": 1
            },
            {
                "command": "PRINT_DIALOG",
                "args": [ "Satan?!\n\nThat's what Basileus was after!", "1" ],
                "end": 1
            },
            {
                "command": "DIALOG_FADEOUT",
                "args": [],
                "end": 1
            },
            {
                "command": "SET_CHARA",
                "args": [ "102801", "8", "9" ],
                "end": 1
            },
            {
                "command": "DIALOG_FADEIN",
                "args": [],
                "end": 1
            },
            {
                "command": "SET_SPEAKER",
                "args": [ "Nevin" ],
                "end": 1
            },
            {
                "command": "PLAY_VOICE",
                "args": [ "VO_STY_100002_015", "1", "8", "9", "8", "9"],
                "end": 1
            },
            {
                "command": "PRINT_DIALOG",
                "args": [ "Anything useful about Satan's resurrection written in there?", "1" ],
                "end": 1
            },
            {
                "command": "DIALOG_FADEOUT",
                "args": [],
                "end": 1
            },
            {
                "command": "SET_CHARA",
                "args": [ "2011","0","7"],
                "end": 1
            },
            {
                "command": "DIALOG_FADEIN",
                "args": [],
                "end": 1
            },
            {
                "command": "SET_SPEAKER",
                "args": [ "Gabriel" ],
                "end": 1
            },
            {
                "command": "PLAY_VOICE",
                "args": [ "VO_STY_100002_016", "1", "8", "7"],
                "end": 1
            },
            {
                "command": "PRINT_DIALOG",
                "args": [ "Hold on, let me see...", "1" ],
                "end": 1
            },
            {
                "command": "DIALOG_FADEOUT",
                "args": [],
                "end": 1
            },
            {
                "command": "PLAY_SE",
                "args": [ "STORY_COMMON_0022", "1" ],
                "end": 1
            },
            {
                "command": "SET_CHARA",
                "args": [ "2011","0","8","0","-108.0","1" ],
                "end": 1
            },
            {
                "command": "WAIT",
                "args": [0.6],
                "end": 1
            },
            {
                "command": "DIALOG_FADEIN",
                "args": [],
                "end": 1
            },
            {
                "command": "SET_SPEAKER",
                "args": [ "Gabriel" ],
                "end": 1
            },
            {
                "command": "PLAY_VOICE",
                "args": [ "VO_STY_100002_017", "1", "8", "7"],
                "end": 1
            },
            {
                "command": "PRINT_DIALOG",
                "args": [ "Right, okay. This says the Five Archdemons were originally derived from Satan and\n\nhold fragments of his flesh inside them.", "1" ],
                "end": 1
            },
            {
                "command": "CLEAR_DIALOG",
                "args": [0],
                "end": 1
            },
            {
                "command": "PLAY_VOICE",
                "args": [ "VO_STY_100002_018", "1", "8", "7"],
                "end": 1
            },
            {
                "command": "PRINT_DIALOG",
                "args": [ "Those fragments need a vessel to serve as their heart and drive them, so...\n\nOh, hang on. There's a note in the margin.", "1" ],
                "end": 1
            },
            {
                "command": "CLEAR_DIALOG",
                "args": [0],
                "end": 1
            },
            {
                "command": "PLAY_VOICE",
                "args": [ "VO_STY_100002_019", "1", "8", "7"],
                "end": 1
            },
            {
                "command": "PRINT_DIALOG",
                "args": [ "'Flesh and heart alone may not suffice.\n\nWhat about the soul? Further investigation is required.'", "1" ],
                "end": 1
            },
            {
                "command": "DIALOG_FADEOUT",
                "args": [],
                "end": 1
            },
            {
                "command": "SET_CHARA",
                "args": [ "102801", "8", "14" ],
                "end": 1
            },
            {
                "command": "DIALOG_FADEIN",
                "args": [],
                "end": 1
            },
            {
                "command": "SET_SPEAKER",
                "args": [ "Nevin" ],
                "end": 1
            },
            {
                "command": "PLAY_VOICE",
                "args": [ "VO_STY_100002_020", "1", "14", "15", "8", "9"],
                "end": 1
            },
            {
                "command": "PRINT_DIALOG",
                "args": [ "Wish that last part made more sense, but at least we've got some intel on Satan's revival now.\n\nRamiel, you'd better report this back to Sandalphon.", "1" ],
                "end": 1
            },
            {
                "command": "DIALOG_FADEOUT",
                "args": [],
                "end": 1
            },
            {
                "command": "SET_CHARA",
                "args": [ "2012", "0", "1" ,"0.0","-108.0","1"],
                "end": 1
            },
            {
                "command": "WAIT",
                "args": [0.3],
                "end": 1
            },
            {
                "command": "SET_CHARA_FACE",
                "args": [ "2012", "1", "0" , 1 ],
                "end": 1
            },
            {
                "command": "PLAY_SE",
                "args": [ "STORY_COMMON_0383", "1" ],
                "end": 1
            },
            {
                "command": "WAIT",
                "args": [1.2],
                "end": 1
            },
            {
                "command": "SET_CHARA_FACE",
                "args": [ "2012", "6", "9" , 1 ],
                "end": 1
            },
            {
                "command": "PORTRAIT_MOVE",
                "args": [ "SHAKE", "20", "0.5"],
                "end": 1
            },
            {
                "command": "WAIT",
                "args": [0.4],
                "end": 1
            },
            {
                "command": "SET_CHARA",
                "args": [ "2012", "7", "9" ,"0.0","-108.0","0"],
                "end": 1
            },
            {
                "command": "DIALOG_FADEIN",
                "args": [],
                "end": 1
            },
            {
                "command": "SET_SPEAKER",
                "args": [ "Ramiel" ],
                "end": 1
            },
            {
                "command": "PLAY_VOICE",
                "args": [ "VO_STY_100002_021", "1", "8", "9"],
                "end": 1
            },
            {
                "command": "PRINT_DIALOG",
                "args": [ "...I can't!\n\nSome kind of barrier is cutting off my link to her!", "1" ],
                "end": 1
            },
            {
                "command": "DIALOG_FADEOUT",
                "args": [],
                "end": 1
            },
            {
                "command": "SET_CHARA",
                "args": [ "102801", "4", "14" ],
                "end": 1
            },
            {
                "command": "DIALOG_FADEIN",
                "args": [],
                "end": 1
            },
            {
                "command": "SET_SPEAKER",
                "args": [ "Nevin" ],
                "end": 1
            },
            {
                "command": "PLAY_VOICE",
                "args": [ "VO_STY_100002_022", "1", "14", "15", "4", "5"],
                "end": 1
            },
            {
                "command": "PRINT_DIALOG",
                "args": [ "What?!", "1" ],
                "end": 1
            },
            {
                "command": "DIALOG_FADEOUT",
                "args": [],
                "end": 1
            },
            {
                "command": "SET_CHARA",
                "args": [ "101801", "12", "13"],
                "end": 1
            },
            {
                "command": "DIALOG_FADEIN",
                "args": [],
                "end": 1
            },
            {
                "command": "SET_SPEAKER",
                "args": [ "Pinon" ],
                "end": 1
            },
            {
                "command": "PLAY_VOICE",
                "args": [ "VO_STY_100002_023", "1", "13", "14" , "12","13" ],
                "end": 1
            },
            {
                "command": "PRINT_DIALOG",
                "args": [ "Just like what happened in Paradise.\n\nSo does that mean—", "1" ],
                "end": 1
            },
            {
                "command": "DIALOG_FADEOUT",
                "args": [],
                "end": 1
            },
            {
                "command": "FADE_BGM",
                "args": [ 0 , 1 ],
                "end": 1
            },
            {
                "command": "PLAY_SE",
                "args": [ "STORY_COMMON_1001", "1" ],
                "end": 1
            },
            {
                "command": "SET_CHARA_FACE",
                "args": ["101801","8","0"],
                "end": 1
            },
            {
                "command": "SCREEN_SHAKE",
                "args": ["1.5", "20.0"],
                "end": 1
            },
            {
                "command": "PLAY_BGM",
                "args": [ "BGM_STY_0802"],
                "end": 1
            },
            {
                "command": "FADE_BGM",
                "args": [ 1 , 0.5 ],
                "end": 1
            },
            {
                "command": "SET_CHARA",
                "args": [ "2011", "8", "7" ,"0.0","-108.0","0"],
                "end": 1
            },
            {
                "command": "DIALOG_FADEIN",
                "args": [],
                "end": 1
            },
            {
                "command": "SET_SPEAKER",
                "args": [ "Gabriel" ],
                "end": 1
            },
            {
                "command": "PLAY_VOICE",
                "args": [ "VO_STY_100002_024", "1", "8", "7" , "8", "9" ],
                "end": 1
            },
            {
                "command": "PRINT_DIALOG",
                "args": [ "That was an explosion!", "1" ],
                "end": 1
            },
            {
                "command": "DIALOG_FADEOUT",
                "args": [],
                "end": 1
            },
            {
                "command": "SET_CHARA",
                "args": [ "102801", "4", "16" ,"0.0","-108.0","0"],
                "end": 1
            },
            {
                "command": "DIALOG_FADEIN",
                "args": [],
                "end": 1
            },
            {
                "command": "SET_SPEAKER",
                "args": [ "Nevin" ],
                "end": 1
            },
            {
                "command": "PLAY_VOICE",
                "args": [ "VO_STY_100002_025", "1", "16", "17" , "4", "5" ],
                "end": 1
            },
            {
                "command": "PRINT_DIALOG",
                "args": [ "The timing of that barrier and the blast line up too well to be a coincidence.\n\nPapa Bear smells a trap.", "1" ],
                "end": 1
            },
            {
                "command": "DIALOG_FADEOUT",
                "args": [],
                "end": 1
            },
            {
                "command": "SET_CHARA",
                "args": [ "101801", "0", "9" ,"0.0","-108.0","1"],
                "end": 1
            },
            {
                "command": "DIALOG_FADEIN",
                "args": [],
                "end": 1
            },
            {
                "command": "SET_SPEAKER",
                "args": [ "Pinon" ],
                "end": 1
            },
            {
                "command": "PLAY_VOICE",
                "args": [ "VO_STY_100002_026", "1", "9", "10"],
                "end": 1
            },
            {
                "command": "PRINT_DIALOG",
                "args": [ "We need to get out of here. Now!", "1" ],
                "end": 1
            },
            {
                "command": "DIALOG_FADEOUT",
                "args": [],
                "end": 1
            },
            {
                "command": "TRANSFORM_BLACKSCREEN",
                "args": [ "0", "RIGHT", "0.5" ],
                "end": 1
            },
            {
                "command": "PLAY_SE",
                "args": [ "STORY_COMMON_0086", "1" ],
                "end": 1
            },
            {
                "command": "WAIT",
                "args": [0.5],
                "end": 1
            },
            {
                "command": "SET_BACKGROUND",
                "args": [ "sty_bg_04", -64],
                "end": 1
            },
            {
                "command": "SET_BACKGROUND",
                "args": [ "sty_bg_04", -64],
                "end": 1
            },
            {
                "command": "EFFECTS",
                "args": [ "2" , "0" , "-128"],
                "end": 1
            },
            {
                "command": "CHARA_FADE",
                "args": [],
                "end": 1
            },
            {
                "command": "TRANSFORM_BLACKSCREEN",
                "args": [ "1", "RIGHT", "0.5" ],
                "end": 1
            },
            {
                "command": "PLAY_SE",
                "args": [ "STORY_COMMON_0019", "1" ],
                "end": 1
            },
            {
                "command": "WAIT",
                "args": [2.5],
                "end": 1
            },
            {
                "command": "SET_CHARA",
                "args": [ "201202", "0", "0" ],
                "end": 1
            },
            {
                "command": "PLAY_SE",
                "args": [ "STORY_COMMON_0076", "1" ],
                "end": 1
            },
            {
                "command": "WAIT",
                "args": [1.25],
                "end": 1
            },
            {
                "command": "EFFECTS",
                "args": [ "4" ],
                "end": 1
            },
            {
                "command": "PORTRAIT_MOVE",
                "args": [ "ZOOM","1.3","1","0.25","InOutSine" ],
                "end": 1
            },
            {
                "command": "WAIT",
                "args": [0.25],
                "end": 1
            },
            {
                "command": "SET_CHARA",
                "args": [ "8002", "5", "6" ],
                "end": 1
            },
            {
                "command": "DIALOG_FADEIN",
                "args": [],
                "end": 1
            },
            {
                "command": "SET_SPEAKER",
                "args": ["Woman"],
                "end": 1
            },
            {
                "command": "PLAY_VOICE",
                "args": [ "VO_STY_100002_027", "1", "6", "7" , "5", "6" ],
                "end": 1
            },
            {
                "command": "PRINT_DIALOG",
                "args": [ "Aaaaah! Please save me!", "1" ],
                "end": 1
            },
            {
                "command": "DIALOG_FADEOUT",
                "args": [],
                "end": 1
            },
            {
                "command": "EFFECTS",
                "args": [ "3" ],
                "end": 1
            },
            {
                "command": "SET_CHARA_FACE",
                "args": [ "8002", "6" , "7" , 1 ],
                "end": 1
            },
            {
                "command": "SCREEN_SHAKE",
                "args": ["0.2", "10.0"],
                "end": 1
            },
            {
                "command": "WAIT",
                "args": [ 1 ],
                "end": 1
            },
            {
                "command": "PORTRAIT_MOVE",
                "args": [ "MOVE","-25","-128","0.3" ],
                "end": 1
            },
            {
                "command": "WAIT",
                "args": [0.2],
                "end": 1
            },
            {
                "command": "PORTRAIT_MOVE",
                "args": [ "MOVE","25","-200","0.7" ],
                "end": 1
            },
            {
                "command": "WAIT",
                "args": [0.3],
                "end": 1
            },
            {
                "command": "PORTRAIT_MOVE",
                "args": [ "MOVE","0","-250","0.3" ],
                "end": 1
            },
            {
                "command": "PORTRAIT_MOVE",
                "args": [ "MOVE","0","-450","0.5" ],
                "end": 1
            },
            {
                "command": "PLAY_SE",
                "args": [ "STORY_COMMON_0060", "1" ],
                "end": 1
            },
            {
                "command": "WAIT",
                "args": [0.5],
                "end": 1
            },
            {
                "command": "CHARA_FADE",
                "args": [],
                "end": 1
            },
            {
                "command": "TRANSFORM_BLACKSCREEN",
                "args": [ "0", "LEFT", "1.0" ],
                "end": 1
            },
            {
                "command": "WAIT",
                "args": [0.5],
                "end": 1
            },
            {
                "command": "DESTROY_PORTRAIT",
                "args": [ "8002" ],
                "end": 1
            },
            {
                "command": "SET_CHARA",
                "args": [ "8003", "7", "9" , "-1024" ,"-108" ],
                "end": 1
            },
            {
                "command": "TRANSFORM_BLACKSCREEN",
                "args": [ "1", "LEFT", "1.0" ],
                "end": 1
            },
            {
                "command": "PORTRAIT_MOVE",
                "args": [ "WALK", "15", "-1024", "0.0", "1" ],
                "end": 1
            },
            {
                "command": "DIALOG_FADEIN",
                "args": [],
                "end": 1
            },
            {
                "command": "SET_SPEAKER",
                "args": ["Man"],
                "end": 1
            },
            {
                "command": "PLAY_VOICE",
                "args": [ "VO_STY_100002_028", "1", "9", "10" , "7", "8" ],
                "end": 1
            },
            {
                "command": "PRINT_DIALOG",
                "args": [ "Angels?! But why?!\n\nAaaaaargh!", "1" ],
                "end": 1
            },
            {
                "command": "DIALOG_FADEOUT",
                "args": [],
                "end": 1
            },
            {
                "command": "WAIT",
                "args": [0.5],
                "end": 1
            },
            {
                "command": "ADD_CHARA",
                "args": [ "201302","-1200" ],
                "end": 1
            },
            {
                "command": "PORTRAIT_MOVE",
                "args": [ "MOVE","-100","-108","0.3","OutSine" ],
                "end": 1
            },
            {
                "command": "EFFECTS",
                "args": [ "5" ],
                "end": 1
            },
            {
                "command": "SET_CHARA_FACE",
                "args": [ "8003", "10", "7" , 1 ],
                "end": 1
            },
            {
                "command": "SWITCH_SPEAKER",
                "args": [ "8003" ],
                "end": 1
            },
            {
                "command": "PORTRAIT_MOVE",
                "args": [ "MOVE","1600","-108","0.6","OutQuad" ],
                "end": 1
            },
            {
                "command": "SCREEN_SHAKE",
                "args": ["0.4", "12.0"],
                "end": 1
            },
            {
                "command": "BLACKIN",
                "args": [],
                "end": 1
            },
            {
                "command": "DESTROY_EFFECTS",
                "args": [ "2" ],
                "end": 1
            },
            {
                "command": "DESTROY_PORTRAIT",
                "args": [ "8003" ],
                "end": 1
            },
            {
                "command": "SET_CHARA",
                "args": [ "101801", "8", "7" ],
                "end": 1
            },
            {
                "command": "BLACKOUT",
                "args": [],
                "end": 1
            },
            {
                "command": "SET_CHARA",
                "args": [ "101801", "8", "7","0","-108.0","0" ],
                "end": 1
            },
            {
                "command": "DIALOG_FADEIN",
                "args": [],
                "end": 1
            },
            {
                "command": "SET_SPEAKER",
                "args": [ "Pinon" ],
                "end": 1
            },
            {
                "command": "PLAY_VOICE",
                "args": [ "VO_STY_100002_029","1","7","8","6","7" ],
                "end": 1
            },
            {
                "command": "PRINT_DIALOG",
                "args": [ "This is a slaughter...!" , 1],
                "end": 1
            },
            {
                "command": "DIALOG_FADEOUT",
                "args": [],
                "end": 1
            },
            {
                "command": "SET_CHARA",
                "args": [ "2012", "7", "9" ,"0.0","-108.0","0"],
                "end": 1
            },
            {
                "command": "DIALOG_FADEIN",
                "args": [],
                "end": 1
            },
            {
                "command": "SET_SPEAKER",
                "args": [ "Ramiel" ],
                "end": 1
            },
            {
                "command": "PLAY_VOICE",
                "args": [ "VO_STY_100002_030", "1", "8", "9"],
                "end": 1
            },
            {
                "command": "PRINT_DIALOG",
                "args": [ "See how they bear our form?\n\nThese are clearly the same demonic entities we fought previously.", "1" ],
                "end": 1
            },
            {
                "command": "DIALOG_FADEOUT",
                "args": [],
                "end": 1
            },
            {
                "command": "SET_CHARA",
                "args": [ "2011", "8", "12" ,"0.0","-108.0","0"],
                "end": 1
            },
            {
                "command": "DIALOG_FADEIN",
                "args": [],
                "end": 1
            },
            {
                "command": "SET_SPEAKER",
                "args": [ "Gabriel" ],
                "end": 1
            },
            {
                "command": "PLAY_VOICE",
                "args": [ "VO_STY_100002_031", "1", "12", "13" , "8", "9" ],
                "end": 1
            },
            {
                "command": "PRINT_DIALOG",
                "args": [ "Such numbers...\n\nJust how many people did they expose to the miasma?!", "1" ],
                "end": 1
            },
            {
                "command": "DIALOG_FADEOUT",
                "args": [],
                "end": 1
            },
            {
                "command": "WAIT",
                "args": [ 1 ],
                "end": 1
            },
            {
                "command": "CHARA_FADE",
                "args": [],
                "end": 1
            },
            {
                "command": "DIALOG_FADEIN",
                "args": [],
                "end": 1
            },
            {
                "command": "SET_SPEAKER",
                "args": [ "???" ],
                "end": 1
            },
            {
                "command": "PLAY_VOICE",
                "args": [ "VO_STY_100002_032"],
                "end": 1
            },
            {
                "command": "PRINT_DIALOG",
                "args": [ "Necessary sacrifices to protect this world,\n\nI'm afraid.", "1" ],
                "end": 1
            },
            {
                "command": "DIALOG_FADEOUT",
                "args": [],
                "end": 1
            },
            {
                "command": "SET_CHARA",
                "args": [ "102801", "4", "16" ],
                "end": 1
            },
            {
                "command": "DIALOG_FADEIN",
                "args": [],
                "end": 1
            },
            {
                "command": "SET_SPEAKER",
                "args": [ "Nevin" ],
                "end": 1
            },
            {
                "command": "PLAY_VOICE",
                "args": [ "VO_STY_100002_033", "1", "16", "17" , "4", "5"],
                "end": 1
            },
            {
                "command": "PRINT_DIALOG",
                "args": [ "Should have known I'd find you\n\nslinking around this business, Basileus!", "1" ],
                "end": 1
            },
            {
                "command": "DIALOG_FADEOUT",
                "args": [],
                "end": 1
            },
            {
                "command": "TRANSFORM_BLACKSCREEN",
                "args": [ "0", "RIGHT", "0.75" ],
                "end": 1
            },
            {
                "command": "PLAY_SE",
                "args": [ "STORY_COMMON_0065", "1" ],
                "end": 1
            },
            {
                "command": "SET_CHARA",
                "args": [ "102601" ],
                "end": 1
            },
            {
                "command": "TRANSFORM_BLACKSCREEN",
                "args": [ "1", "RIGHT", "0.75" ],
                "end": 1
            },
            {
                "command": "DIALOG_FADEIN",
                "args": [],
                "end": 1
            },
            {
                "command": "SET_SPEAKER",
                "args": [ "Basileus" ],
                "end": 1
            },
            {
                "command": "PLAY_VOICE",
                "args": [ "VO_STY_100002_034", "1", "0", "1"],
                "end": 1
            },
            {
                "command": "PRINT_DIALOG",
                "args": [ "I had faith you would all arrive here.", "1" ],
                "end": 1
            },
            {
                "command": "DIALOG_FADEOUT",
                "args": [],
                "end": 1
            },
            {
                "command": "SET_CHARA",
                "args": [ "102801", "8", "14" ],
                "end": 1
            },
            {
                "command": "DIALOG_FADEIN",
                "args": [],
                "end": 1
            },
            {
                "command": "SET_SPEAKER",
                "args": [ "Nevin" ],
                "end": 1
            },
            {
                "command": "PLAY_VOICE",
                "args": [ "VO_STY_100002_035", "1", "14", "15", "8", "9"],
                "end": 1
            },
            {
                "command": "PRINT_DIALOG",
                "args": [ "Well, can't say I approve of your taste in welcoming parties.", "1" ],
                "end": 1
            },
            {
                "command": "DIALOG_FADEOUT",
                "args": [],
                "end": 1
            },
            {
                "command": "SET_CHARA",
                "args": [ "101801", "2", "9"],
                "end": 1
            },
            {
                "command": "DIALOG_FADEIN",
                "args": [],
                "end": 1
            },
            {
                "command": "SET_SPEAKER",
                "args": [ "Pinon" ],
                "end": 1
            },

            {
                "command": "PLAY_VOICE",
                "args": [ "VO_STY_100002_036", "1", "9", "10" , "2","3" ],
                "end": 1
            },
            {
                "command": "PRINT_DIALOG",
                "args": [ "Basileus! You monster!", "1" ],
                "end": 1
            },
            {
                "command": "DIALOG_FADEOUT",
                "args": [],
                "end": 1
            },
            {
                "command": "WAIT",
                "args": [ 0.25 ],
                "end": 1
            },
            {
                "command": "PLAY_SE",
                "args": [ "STORY_COMMON_0012", "1" ],
                "end": 1
            },
            {
                "command": "SET_CHARA",
                "args": [ "101802", "0", "0"],
                "end": 1
            },
            {
                "command": "WAIT",
                "args": [ 0.75 ],
                "end": 1
            },
            {
                "command": "PLAY_SE",
                "args": [ "STORY_COMMON_0046", "1" ],
                "end": 1
            },
            {
                "command": "PORTRAIT_MOVE",
                "args": [ "ZOOM","1.4","1","0.2","InOutSine" ],
                "end": 1
            },
            {
                "command": "WAIT",
                "args": [ 0.25 ],
                "end": 1
            },
            {
                "command": "SET_CHARA",
                "args": [ "102601" ],
                "end": 1
            },
            {
                "command": "WAIT",
                "args": [ 0.75 ],
                "end": 1
            },
            {
                "command": "EFFECTS",
                "args": [ "6" ],
                "end": 1
            },
            {
                "command": "PORTRAIT_MOVE",
                "args": [ "MOVE","300","-158","0.3","OutSine" ],
                "end": 1
            },
            {
                "command": "WAIT",
                "args": [ 0.85 ],
                "end": 1
            },
            {
                "command": "SET_CHARA",
                "args": [ "101802", "3", "7"],
                "end": 1
            },
            {
                "command": "DIALOG_FADEIN",
                "args": [],
                "end": 1
            },
            {
                "command": "SET_SPEAKER",
                "args": [ "Pinon" ],
                "end": 1
            },

            {
                "command": "PLAY_VOICE",
                "args": [ "VO_STY_100002_037", "1", "7", "8" , "3","4" ],
                "end": 1
            },
            {
                "command": "PRINT_DIALOG",
                "args": [ "How could you do such a thing?!", "1" ],
                "end": 1
            },
            {
                "command": "DIALOG_FADEOUT",
                "args": [],
                "end": 1
            },
            {
                "command": "SET_CHARA",
                "args": [ "102601", "1", "0"],
                "end": 1
            },
            {
                "command": "DIALOG_FADEIN",
                "args": [],
                "end": 1
            },
            {
                "command": "SET_SPEAKER",
                "args": [ "Basileus" ],
                "end": 1
            },
            {
                "command": "PLAY_VOICE",
                "args": [ "VO_STY_100002_038", "1", "0", "1" , "1", "1" ],
                "end": 1
            },
            {
                "command": "PRINT_DIALOG",
                "args": [ "Actually, it was your meddling in my plans that forced my hand.", "1" ],
                "end": 1
            },
            {
                "command": "DIALOG_FADEOUT",
                "args": [],
                "end": 1
            },
            {
                "command": "FADE_BGM",
                "args": [ 0 , 1 ],
                "end": 1
            },
            {
                "command": "SET_CHARA",
                "args": [ "2011", "4", "12"],
                "end": 1
            },
            {
                "command": "DIALOG_FADEIN",
                "args": [],
                "end": 1
            },
            {
                "command": "SET_SPEAKER",
                "args": [ "Gabriel" ],
                "end": 1
            },
            {
                "command": "PLAY_VOICE",
                "args": [ "VO_STY_100002_039", "1", "12", "13" , "4", "5" ],
                "end": 1
            },
            {
                "command": "PRINT_DIALOG",
                "args": [ "Your plan to revive Satan, you mean.", "1" ],
                "end": 1
            },
            {
                "command": "DIALOG_FADEOUT",
                "args": [],
                "end": 1
            },
            {
                "command": "SET_CHARA",
                "args": [ "102601", "0", "0"],
                "end": 1
            },
            {
                "command": "DIALOG_FADEIN",
                "args": [],
                "end": 1
            },
            {
                "command": "PLAY_BGM",
                "args": [ "BGM_STY_EV_001" ],
                "end": 1
            },
            {
                "command": "FADE_BGM",
                "args": [ 1 , 2 ],
                "end": 1
            },
            {
                "command": "SET_SPEAKER",
                "args": [ "Basileus" ],
                "end": 1
            },
            {
                "command": "PLAY_VOICE",
                "args": [ "VO_STY_100002_040", "1", "0", "1"],
                "end": 1
            },
            {
                "command": "PRINT_DIALOG",
                "args": [ "Yes. Once the sealed archdemons were all released from their mimicries,\n\nmy plan entered its final phase.", "1" ],
                "end": 1
            },
            {
                "command": "DIALOG_FADEOUT",
                "args": [],
                "end": 1
            },
            {
                "command": "SET_CHARA",
                "args": [ "2012", "0", "4" ,"0.0","-108.0","0"],
                "end": 1
            },
            {
                "command": "DIALOG_FADEIN",
                "args": [],
                "end": 1
            },
            {
                "command": "SET_SPEAKER",
                "args": [ "Ramiel" ],
                "end": 1
            },
            {
                "command": "PLAY_VOICE",
                "args": [ "VO_STY_100002_041", "1", "4", "5"],
                "end": 1
            },
            {
                "command": "PRINT_DIALOG",
                "args": [ "There are a host of conditions for bringing back Satan.\n\nAre you truly claiming to havealready met them all?", "1" ],
                "end": 1
            },
            {
                "command": "DIALOG_FADEOUT",
                "args": [],
                "end": 1
            },
            {
                "command": "SET_CHARA",
                "args": [ "102601", "0", "0"],
                "end": 1
            },
            {
                "command": "DIALOG_FADEIN",
                "args": [],
                "end": 1
            },
            {
                "command": "SET_SPEAKER",
                "args": [ "Basileus" ],
                "end": 1
            },
            {
                "command": "PLAY_VOICE",
                "args": [ "VO_STY_100002_042", "1", "0", "1"],
                "end": 1
            },
            {
                "command": "PRINT_DIALOG",
                "args": [ "I see you read the journal.\n\nIn that case, allow me to tell you a fun little fact...", "1" ],
                "end": 1
            },
            {
                "command": "CLEAR_DIALOG",
                "args": [0],
                "end": 1
            },
            {
                "command": "PLAY_VOICE",
                "args": [ "VO_STY_100002_043", "1", "0", "1"],
                "end": 1
            },
            {
                "command": "PRINT_DIALOG",
                "args": [ "The vessel required for Satan's revival... is me.", "1" ],
                "end": 1
            },
            {
                "command": "DIALOG_FADEOUT",
                "args": [],
                "end": 1
            },
            {
                "command": "SET_CHARA",
                "args": [ "2011", "4", "12" ,"0.0","-108.0","0"],
                "end": 1
            },
            {
                "command": "DIALOG_FADEIN",
                "args": [],
                "end": 1
            },
            {
                "command": "SET_SPEAKER",
                "args": [ "Gabriel" ],
                "end": 1
            },
            {
                "command": "PLAY_VOICE",
                "args": [ "VO_STY_100002_046", "1", "12", "13", "4", "5" ],
                "end": 1
            },
            {
                "command": "PRINT_DIALOG",
                "args": [ "Are you mad?! You'll never survive that,\n\neven with your strength!", "1" ],
                "end": 1
            },
            {
                "command": "DIALOG_FADEOUT",
                "args": [],
                "end": 1
            },
            {
                "command": "SET_CHARA",
                "args": [ "102601", "0", "0"],
                "end": 1
            },
            {
                "command": "DIALOG_FADEIN",
                "args": [],
                "end": 1
            },
            {
                "command": "SET_SPEAKER",
                "args": [ "Basileus" ],
                "end": 1
            },
            {
                "command": "PLAY_VOICE",
                "args": [ "VO_STY_100002_047", "1", "0", "1"],
                "end": 1
            },
            {
                "command": "PRINT_DIALOG",
                "args": [ "And what of it? Salvation for the world atthe cost of a single life?\n\nI can imagine no greater bargain.", "1" ],
                "end": 1
            },
            {
                "command": "DIALOG_FADEOUT",
                "args": [],
                "end": 1
            },
            {
                "command": "SET_CHARA",
                "args": [ "101802", "3", "9" ,"0.0","-108.0","2"],
                "end": 1
            },
            {
                "command": "DIALOG_FADEIN",
                "args": [],
                "end": 1
            },
            {
                "command": "SET_SPEAKER",
                "args": [ "Pinon" ],
                "end": 1
            },
            {
                "command": "PLAY_VOICE",
                "args": [ "VO_STY_100002_048", "1", "7", "8" , "3","4" ],
                "end": 1
            },
            {
                "command": "PRINT_DIALOG",
                "args": [ "How can you talk about salvation for the world\n\nafter bringing about this massacre?!", "1" ],
                "end": 1
            },
            {
                "command": "DIALOG_FADEOUT",
                "args": [],
                "end": 1
            },
            {
                "command": "SET_CHARA",
                "args": [ "102601", "1", "0"],
                "end": 1
            },
            {
                "command": "DIALOG_FADEIN",
                "args": [],
                "end": 1
            },
            {
                "command": "SET_SPEAKER",
                "args": [ "Basileus" ],
                "end": 1
            },
            {
                "command": "PLAY_VOICE",
                "args": [ "VO_STY_100002_049", "1", "0", "1" , "1", "1" ],
                "end": 1
            },
            {
                "command": "PRINT_DIALOG",
                "args": [ "Because it prevented a far greater tragedy.\n\nIf the deaths of a few ensure the survival of the many, it is immoral not to do so.", "1" ],
                "end": 1
            },
            {
                "command": "DIALOG_FADEOUT",
                "args": [],
                "end": 1
            },
            {
                "command": "SET_CHARA",
                "args": [ "101802", "3", "9" ,"0.0","-108.0","0"],
                "end": 1
            },
            {
                "command": "DIALOG_FADEIN",
                "args": [],
                "end": 1
            },
            {
                "command": "SET_SPEAKER",
                "args": [ "Pinon" ],
                "end": 1
            },
            {
                "command": "PLAY_VOICE",
                "args": [ "VO_STY_100002_050", "1", "7", "8" , "3","4" ],
                "end": 1
            },
            {
                "command": "PRINT_DIALOG",
                "args": [ "Don't you dare speak to me of morality!\n\nSalvation bought with blood is no true salvation at all!", "1" ],
                "end": 1
            },
            {
                "command": "DIALOG_FADEOUT",
                "args": [],
                "end": 1
            },
            {
                "command": "SET_CHARA",
                "args": [ "102601", "0", "0"],
                "end": 1
            },
            {
                "command": "DIALOG_FADEIN",
                "args": [],
                "end": 1
            },
            {
                "command": "SET_SPEAKER",
                "args": [ "Basileus" ],
                "end": 1
            },
            {
                "command": "PLAY_VOICE",
                "args": [ "VO_STY_100002_051", "1", "0", "1"],
                "end": 1
            },
            {
                "command": "PRINT_DIALOG",
                "args": [ "Oh, my sweet, naive Pinon...\n\nYour wordsonly serve to demonstrate what a privileged upbringing you enjoyed.", "1" ],
                "end": 1
            },
            {
                "command": "DIALOG_FADEOUT",
                "args": [],
                "end": 1
            },
            {
                "command": "SET_CHARA",
                "args": [ "101802", "3", "7"],
                "end": 1
            },
            {
                "command": "DIALOG_FADEIN",
                "args": [],
                "end": 1
            },
            {
                "command": "SET_SPEAKER",
                "args": [ "Pinon" ],
                "end": 1
            },
            {
                "command": "PLAY_VOICE",
                "args": [ "VO_STY_100002_052", "1", "7", "8" , "3","4" ],
                "end": 1
            },
            {
                "command": "PRINT_DIALOG",
                "args": [ "Just what do you mean by that?!", "1" ],
                "end": 1
            },
            {
                "command": "DIALOG_FADEOUT",
                "args": [],
                "end": 1
            },
            {
                "command": "SET_CHARA",
                "args": [ "102601", "1", "0"],
                "end": 1
            },
            {
                "command": "DIALOG_FADEIN",
                "args": [],
                "end": 1
            },
            {
                "command": "SET_SPEAKER",
                "args": [ "Basileus" ],
                "end": 1
            },
            {
                "command": "PLAY_VOICE",
                "args": [ "VO_STY_100002_053", "1", "0", "1" , "1", "1" ],
                "end": 1
            },
            {
                "command": "PRINT_DIALOG",
                "args": [ "I have nothing further to say.", "1" ],
                "end": 1
            },
            {
                "command": "DIALOG_FADEOUT",
                "args": [],
                "end": 1
            },
            {
                "command": "SET_CHARA",
                "args": [ "2012", "0", "0"],
                "end": 1
            },
            {
                "command": "DIALOG_FADEIN",
                "args": [],
                "end": 1
            },
            {
                "command": "SET_SPEAKER",
                "args": [ "Ramiel" ],
                "end": 1
            },
            {
                "command": "PLAY_VOICE",
                "args": [ "VO_STY_100002_054", "1", "0", "1"],
                "end": 1
            },
            {
                "command": "PRINT_DIALOG",
                "args": [ "I'm afraid we aren't done speaking until you answer all of our questions.\n\n...Nevin!", "1" ],
                "end": 1
            },
            {
                "command": "DIALOG_FADEOUT",
                "args": [],
                "end": 1
            },
            {
                "command": "SET_CHARA",
                "args": [ "102801", "0", "0","0","-108","1"],
                "end": 1
            },
            {
                "command": "DIALOG_FADEIN",
                "args": [],
                "end": 1
            },
            {
                "command": "SET_SPEAKER",
                "args": [ "Nevin" ],
                "end": 1
            },
            {
                "command": "PLAY_VOICE",
                "args": [ "VO_STY_100002_055", "1", "0", "1" ],
                "end": 1
            },
            {
                "command": "PRINT_DIALOG",
                "args": [ "On it. Sigil, unleash!", "1" ],
                "end": 1
            },
            {
                "command": "DIALOG_FADEOUT",
                "args": [],
                "end": 1
            },
            {
                "command": "SET_CHARA",
                "args": [ "102802", "0", "0"],
                "end": 1
            },
            {
                "command": "EFFECTS",
                "args": ["7"],
                "end": 1
            },
            {
                "command": "PLAY_SE",
                "args": [ "STORY_COMMON_0012", "1" ],
                "end": 1
            },
            {
                "command": "WAIT",
                "args": [0.5],
                "end": 1
            },
            {
                "command": "DIALOG_FADEIN",
                "args": [],
                "end": 1
            },
            {
                "command": "SET_SPEAKER",
                "args": [ "Nevin" ],
                "end": 1
            },
            {
                "command": "PLAY_VOICE",
                "args": [ "VO_STY_100002_056", "1", "0", "1" ],
                "end": 1
            },
            {
                "command": "PRINT_DIALOG",
                "args": [ "Sorry, Basileus,\n\nbut we're in a bit of a hurry and I need to end this!", "1" ],
                "end": 1
            },
            {
                "command": "DIALOG_FADEOUT",
                "args": [],
                "end": 1
            },
            {
                "command": "BUTTON_VISIBILITY",
                "args": [ "0" ],
                "end": 1
            },
            {
                "command": "BLACKIN",
                "args": [],
                "end": 1
            }
        ],
        "content": "Nevin's team infiltrates Rozcimea to gather intel on the demonic incidents, but no sooner do they find a lead than Basileus appears with demonic entities in tow.",
        "jump_action": "battle",
        "jump_arg": 100002,
        "resources": []
    }
}